{
    "name": "Drawbridge Dark",
    "comment": "Base2Tone Drawbridge dark variation",
    "foreground-color": "#9094a7",
    "background-color": "#1b1f32",
    "use-theme-colors": false,
    "use-cursor-color": false,
    "cursor-foreground-color": "#1b1f32",
    "cursor-background-color": "#9094a7",
    "use-highlight-color": false,
    "highlight-foreground-color": "#1b1f32",
    "highlight-background-color": "#9094a7",
    "use-bold-color": false,
    "bold-color": "#e1e6ff",
    "use-badge-color": false,
    "badge-color": "#67c9ef",
    "palette": [
        "#1b1f32",
        "#627af4",
        "#67c9e4",
        "#99e9ff",
        "#7289fd",
        "#67c9e4",
        "#8b9efd",
        "#9094a7",
        "#51587b",
        "#627af4",
        "#67c9e4",
        "#99e9ff",
        "#7289fd",
        "#67c9e4",
        "#8b9efd",
        "#e1e6ff"
    ]
}
